cromo/__init__.py
cromo/__main__.py
cromo/_utils.py
cromo/constants.py
cromo/catalogs/__init__.py
cromo/catalogs/data_catalog.py
cromo/catalogs/model_catalog.py
cromo/click_encapsulate/__init__.py
cromo/click_encapsulate/commands.py
cromo/metadata/__init__.py
cromo/metadata/sensors.py
cromo-1.1.3.dist-info/METADATA
cromo-1.1.3.dist-info/WHEEL
cromo-1.1.3.dist-info/entry_points.txt
cromo-1.1.3.dist-info/top_level.txt
cromo-1.1.3.dist-info/RECORD
